langchain_pdf/__init__.py
langchain_pdf/base.py
langchain_pdf/blocks.py
langchain_pdf/cli.py
langchain_pdf/exporter.py
langchain_pdf/llm_factory.py
langchain_pdf/normalizer.py
langchain_pdf/parser.py
langchain_pdf/renderer.py
langchain_pdf/templates.py
langchain_pdf/assets/fonts/DejaVuSans-Bold.ttf
langchain_pdf/assets/fonts/Inter_18pt-Bold.ttf
langchain_pdf/assets/fonts/Inter_18pt-Regular.ttf
langchain_pdf/assets/fonts/LICENSE.txt
langchain_pdf-0.2.0.dist-info/licenses/LICENSE
langchain_pdf-0.2.0.dist-info/METADATA
langchain_pdf-0.2.0.dist-info/WHEEL
langchain_pdf-0.2.0.dist-info/entry_points.txt
langchain_pdf-0.2.0.dist-info/top_level.txt
langchain_pdf-0.2.0.dist-info/RECORD
