Metadata-Version: 2.4
Name: langchain-pdf
Version: 0.2.0
Summary: Generate clean, readable PDFs from raw text or LLM output
Author: Dev Doshi
License: MIT
Keywords: langchain,llm,pdf,generative-ai,document-generation
Classifier: Development Status :: 3 - Alpha
Classifier: Intended Audience :: Developers
Classifier: License :: OSI Approved :: MIT License
Classifier: Programming Language :: Python :: 3
Classifier: Programming Language :: Python :: 3.9
Classifier: Programming Language :: Python :: 3.10
Classifier: Programming Language :: Python :: 3.11
Classifier: Operating System :: OS Independent
Requires-Python: >=3.9
License-File: LICENSE
Requires-Dist: fpdf2
Requires-Dist: langchain
Requires-Dist: python-dotenv
Dynamic: license-file
